LICENSE
setup.cfg
setup.py
tests/__init__.py
tests/test_widget.py
toscawidgets/__init__.py
toscawidgets/widgets/__init__.py
toscawidgets/widgets/ajax_tools/__init__.py
toscawidgets/widgets/ajax_tools/release.py
toscawidgets/widgets/ajax_tools/samples.py
toscawidgets/widgets/ajax_tools/widgets.py
toscawidgets/widgets/ajax_tools/extensions/__init__.py
toscawidgets/widgets/ajax_tools/extensions/tg.py
toscawidgets/widgets/ajax_tools/static/ajax_form.js
toscawidgets/widgets/ajax_tools/static/autocompletefield.css
toscawidgets/widgets/ajax_tools/static/autocompletingfklookup.js
toscawidgets/widgets/ajax_tools/static/common.css
toscawidgets/widgets/ajax_tools/static/updatingselectfield.js
toscawidgets/widgets/ajax_tools/templates/__init__.py
toscawidgets/widgets/ajax_tools/templates/auto_completing_fk_lookup_field.html
toscawidgets/widgets/ajax_tools/templates/table_form.html
toscawidgets/widgets/ajax_tools/templates/updatable_single_select_field.html
twAjaxTools.egg-info/PKG-INFO
twAjaxTools.egg-info/SOURCES.txt
twAjaxTools.egg-info/dependency_links.txt
twAjaxTools.egg-info/entry_points.txt
twAjaxTools.egg-info/namespace_packages.txt
twAjaxTools.egg-info/not-zip-safe
twAjaxTools.egg-info/requires.txt
twAjaxTools.egg-info/top_level.txt