Metadata-Version: 1.0
Name: twAjaxTools
Version: 0.1a1dev-r2199
Summary: Ajax Tools and Widgets for ToscaWidgets
Home-page: UNKNOWN
Author: Claudio Martinez
Author-email: claudio.s.martinez@gmail.com
License: UNKNOWN
Keywords: toscawidgets.widgets
Platform: UNKNOWN
